odoo/addons/sale_stock_picking_note/README.rst
odoo/addons/sale_stock_picking_note/__init__.py
odoo/addons/sale_stock_picking_note/__manifest__.py
odoo/addons/sale_stock_picking_note/i18n/ca.po
odoo/addons/sale_stock_picking_note/i18n/de.po
odoo/addons/sale_stock_picking_note/i18n/es.po
odoo/addons/sale_stock_picking_note/i18n/fr.po
odoo/addons/sale_stock_picking_note/i18n/it.po
odoo/addons/sale_stock_picking_note/i18n/sale_stock_picking_note.pot
odoo/addons/sale_stock_picking_note/i18n/sl.po
odoo/addons/sale_stock_picking_note/i18n/tr.po
odoo/addons/sale_stock_picking_note/models/__init__.py
odoo/addons/sale_stock_picking_note/models/res_partner.py
odoo/addons/sale_stock_picking_note/models/sale_order.py
odoo/addons/sale_stock_picking_note/models/stock_picking.py
odoo/addons/sale_stock_picking_note/readme/CONTRIBUTORS.md
odoo/addons/sale_stock_picking_note/readme/DESCRIPTION.md
odoo/addons/sale_stock_picking_note/readme/USAGE.md
odoo/addons/sale_stock_picking_note/static/description/icon.png
odoo/addons/sale_stock_picking_note/static/description/index.html
odoo/addons/sale_stock_picking_note/tests/__init__.py
odoo/addons/sale_stock_picking_note/tests/test_sale_stock_picking_note.py
odoo/addons/sale_stock_picking_note/views/report_deliveryslip.xml
odoo/addons/sale_stock_picking_note/views/res_partner_view.xml
odoo/addons/sale_stock_picking_note/views/sale_order_view.xml
odoo/addons/sale_stock_picking_note/views/stock_picking_view.xml
odoo_addon_sale_stock_picking_note-19.0.1.0.0.2.dist-info/METADATA
odoo_addon_sale_stock_picking_note-19.0.1.0.0.2.dist-info/WHEEL
odoo_addon_sale_stock_picking_note-19.0.1.0.0.2.dist-info/top_level.txt
odoo_addon_sale_stock_picking_note-19.0.1.0.0.2.dist-info/RECORD
